flowctl/__init__.py
flowctl/__main__.py
flowctl/base.py
flowctl/cli.py
flowctl/client.py
flowctl/commands/__init__.py
flowctl/commands/apply.py
flowctl/commands/config.py
flowctl/commands/delete.py
flowctl/commands/dev/__init__.py
flowctl/commands/dev/utils.py
flowctl/commands/get.py
flowctl/commands/inspect.py
flowctl/commands/metrics.py
flowctl/commands/patch.py
flowctl/commands/run.py
flowctl/commands/status.py
flowctl/config.py
flowctl/constants.py
flowctl/jmespath.py
flowctl/pydantic.py
flowctl/render.py
flowctl/resources.py
flowctl/utils.py
flowctl-0.1.4.dist-info/LICENSE
flowctl-0.1.4.dist-info/METADATA
flowctl-0.1.4.dist-info/WHEEL
flowctl-0.1.4.dist-info/entry_points.txt
flowctl-0.1.4.dist-info/RECORD
