Metadata-Version: 2.3
Name: flowctl
Version: 0.1.4
Summary: The CLI tool for operation of Flowdapt.
License: MIT
Author: Emergent Methods
Author-email: contact@emergentmethods.ai
Requires-Python: >=3.10,<4.0
Classifier: License :: OSI Approved :: MIT License
Classifier: Programming Language :: Python :: 3
Classifier: Programming Language :: Python :: 3.10
Classifier: Programming Language :: Python :: 3.11
Classifier: Programming Language :: Python :: 3.12
Classifier: Programming Language :: Python :: 3.13
Requires-Dist: aiofiles (>=24.1.0,<25.0.0)
Requires-Dist: flowdapt_sdk (>=0.1.1,<0.2.0)
Requires-Dist: humanize (>=4.12.3,<5.0.0)
Requires-Dist: jmespath-community (>=1.1.3,<2.0.0)
Requires-Dist: plotext (>=5.3.2,<6.0.0)
Requires-Dist: python-manifest (>=2.3.3,<3.0.0)
Requires-Dist: rich (>=13.7.0,<14.0.0)
Requires-Dist: typer (>=0.15.2,<0.16.0)
Requires-Dist: typing_extensions (>=4.8.0,<5.0.0)
